ailogx/__init__.py
ailogx/core.py
ailogx/decorators.py
ailogx/handlers.py
ailogx/summarize.py
ailogx/utils.py
ailogx/backends/__init__.py
ailogx/backends/groq.py
ailogx/backends/ollama.py
ailogx/backends/openai.py
ailogx/backends/registry.py
ailogx/cli/analyze_logs.py
ailogx/formatters/structured.py
ailogx/summarizer/cache.py
ailogx/summarizer/chunker.py
ailogx/summarizer/groq_analyzer.py
ailogx/summarizer/summarizer.py
ailogx/summarizer/test.py
ailogx/utils/__init__.py
ailogx/utils/cache.py
ailogx/utils/preprocess.py
ailogx/utils/tokenizer.py
ailogx-1.1.0.dist-info/licenses/LICENSE
ailogx-1.1.0.dist-info/METADATA
ailogx-1.1.0.dist-info/WHEEL
ailogx-1.1.0.dist-info/entry_points.txt
ailogx-1.1.0.dist-info/top_level.txt
ailogx-1.1.0.dist-info/RECORD
