Metadata-Version: 2.4
Name: ailogx
Version: 1.1.0
Summary: LLM-optimized structured logging and summarization for large-scale debugging.
Author: Kunwar Vikrant
Author-email: kunwar.vikrant3@gmail.com
License: Proprietary
Classifier: License :: Other/Proprietary License
Classifier: Programming Language :: Python :: 3
Requires-Python: >=3.7
License-File: LICENSE
Requires-Dist: tiktoken
Requires-Dist: requests
Requires-Dist: rich
Requires-Dist: groq
Requires-Dist: openai
Requires-Dist: ollama
Dynamic: author
Dynamic: author-email
Dynamic: classifier
Dynamic: description
Dynamic: description-content-type
Dynamic: license
Dynamic: license-file
Dynamic: requires-dist
Dynamic: requires-python
Dynamic: summary
